[
  {
    "name": "Volatile Compound",
    "type": "consumable",
    "category": "chemical",
    "quality": "experimental",
    "rarity": "rare",
    "effects": [
      {"type": "custom", "description": "Can be thrown to create a blinding flash and loud bang (stun effect, area)."}
    ],
    "description": "A glass vial containing unstable chemicals. Used for distraction or escape.",
    "artwork": {"image": "", "caption": "A stoppered vial with swirling liquid.", "credit": ""},
    "provenance": "Inspired by period chemical weapons." 
  }
]