[
  {
    "name": "Entrenching Tool",
    "type": "equipment",
    "category": "tool",
    "quality": "standard",
    "rarity": "common",
    "effects": [
      {"type": "custom", "description": "A folding spade for digging trenches, shelters, or graves. Grants advantage on checks to dig or fortify positions."}
    ],
    "description": "A compact, folding shovel carried by soldiers and explorers for fieldwork.",
    "artwork": {"image": "", "caption": "A metal spade with a wooden handle.", "credit": ""},
    "provenance": "Inspired by period military equipment." 
  }
]