{
  "_id": "655a72164fc709a8",
  "name": "Folding Pry Hook",
  "type": "equipment",
  "img": "icons/tools/hand/crowbar-steel.webp",
  "system": {
    "artwork": {
      "image": "icons/svg/item-bag.svg",
      "caption": "Utility item",
      "credit": "Core icon set"
    },
    "commonName": "Pry Hook",
    "description": "<p>A short folding lever for crates, stuck hatches, and iron hasps.</p>",
    "category": "tool",
    "quality": "standard",
    "rarity": "common",
    "slot": "belt",
    "use": {
      "actionCost": 1,
      "requiresHands": true,
      "consumedOnUse": false,
      "skillCheck": {
        "skill": "athletics",
        "difficulty": 11,
        "required": false,
        "purpose": "<p>Force simple barriers and jammed catches.</p>"
      }
    },
    "actions": {
      "defaultActionId": "strikeWithHook",
      "variants": [
        {
          "id": "strikeWithHook",
          "label": "Strike",
          "type": "attack",
          "apCost": 1,
          "requiresToHit": true,
          "toHitBonus": 0,
          "rangeType": "melee",
          "targetSelf": false,
          "targetAlly": false,
          "requiresAdjacency": true,
          "conditions": [],
          "notes": "<p>Quick improvised blow with the folded steel hook. Deals bludgeoning damage.</p>",
          "completionPhaseIncrement": 0,
          "cpiPerFeet": 0,
          "autoResolve": false,
          "interruptible": true,
          "isReaction": false,
          "reactionTriggerType": ""
        },
        {
          "id": "hookAndLever",
          "label": "Hook and Lever",
          "type": "attack",
          "apCost": 2,
          "requiresToHit": true,
          "toHitBonus": 0,
          "rangeType": "melee",
          "targetSelf": false,
          "targetAlly": false,
          "requiresAdjacency": true,
          "conditions": [
            "grappled"
          ],
          "notes": "<p>Hook onto clothing, a belt, or a limb and yank. On hit: target is off-balance (grappled) and loses their footing.</p>",
          "completionPhaseIncrement": 0,
          "cpiPerFeet": 0,
          "autoResolve": false,
          "interruptible": true,
          "isReaction": false,
          "reactionTriggerType": ""
        },
        {
          "id": "leverageOpen",
          "label": "Force Open",
          "type": "utility",
          "apCost": 2,
          "requiresToHit": false,
          "toHitBonus": 0,
          "rangeType": "melee",
          "targetSelf": false,
          "targetAlly": false,
          "requiresAdjacency": true,
          "conditions": [],
          "notes": "<p>Apply the hook to a stuck hatch, crate, or iron fitting and lever it open. Not an attack \u2014 used against objects.</p>",
          "completionPhaseIncrement": 0,
          "cpiPerFeet": 0,
          "autoResolve": false,
          "interruptible": true,
          "isReaction": false,
          "reactionTriggerType": ""
        }
      ]
    },
    "effects": [],
    "physical": {
      "weight": 1.2,
      "bulk": 0,
      "quantity": 1,
      "unit": "tool"
    },
    "value": {
      "price": 3,
      "currency": "pounds"
    },
    "properties": {
      "tags": [
        "breach",
        "utility"
      ],
      "concealable": true,
      "fragile": false,
      "experimental": false,
      "restricted": false
    }
  },
  "flags": {}
}